.env.example
pramen_py/__init__.py
pramen_py/app/__init__.py
pramen_py/app/cli.py
pramen_py/app/logger.py
pramen_py/metastore/__init__.py
pramen_py/metastore/reader.py
pramen_py/metastore/reader_base.py
pramen_py/metastore/writer.py
pramen_py/metastore/writer_base.py
pramen_py/models/__init__.py
pramen_py/models/utils.py
pramen_py/py.typed
pramen_py/runner/__init__.py
pramen_py/runner/runner_base.py
pramen_py/runner/runner_transformation.py
pramen_py/test_utils/__init__.py
pramen_py/test_utils/fixtures.py
pramen_py/test_utils/plugin.py
pramen_py/test_utils/spark_utils.py
pramen_py/test_utils/when.py
pramen_py/transformation/__init__.py
pramen_py/transformation/transformation_base.py
pramen_py/utils/__init__.py
pramen_py/utils/file_system.py
tests/resources/real_config.yaml
transformations/__init__.py
transformations/example_trasformation_one/__init__.py
transformations/example_trasformation_one/some_transformation.py
transformations/example_trasformation_two/__init__.py
transformations/example_trasformation_two/some_transformation.py
transformations/identity_transformer/__init__.py
transformations/identity_transformer/example_config.yaml
pramen_py-1.11.2.dist-info/METADATA
pramen_py-1.11.2.dist-info/WHEEL
pramen_py-1.11.2.dist-info/entry_points.txt
pramen_py-1.11.2.dist-info/RECORD
