Metadata-Version: 2.1
Name: pramen-py
Version: 1.11.2
Summary: Pramen transformations written in python
Home-page: https://github.com/AbsaOSS/pramen
Keywords: paramen,pyspark,transformations,metastore
Author: Artem Zhukov
Author-email: iam@zhukovgreen.pro
Maintainer: Artem Zhukov
Maintainer-email: iam@zhukovgreen.pro
Requires-Python: >=3.6.8,<4.0
Classifier: Programming Language :: Python :: 3
Classifier: Programming Language :: Python :: 3.7
Classifier: Programming Language :: Python :: 3.8
Classifier: Programming Language :: Python :: 3.9
Classifier: Programming Language :: Python :: 3.10
Classifier: Programming Language :: Python :: 3.11
Requires-Dist: PyYAML (>=6.0,<7.0)
Requires-Dist: attrs (>=21.4.0,<22.0.0)
Requires-Dist: cattrs (==1.0.0) ; python_full_version >= "3.6.8" and python_version < "3.7"
Requires-Dist: cattrs (>=22.1.0,<23.0.0) ; python_version >= "3.7" and python_version < "4.0"
Requires-Dist: chispa (>=0.9.2,<0.10.0)
Requires-Dist: click (>=8.0.3,<9.0.0)
Requires-Dist: contextvars (>=2.4,<3.0)
Requires-Dist: environs (>=9.5.0,<10.0.0)
Requires-Dist: loguru (>=0.6.0,<0.7.0)
Requires-Dist: pyhocon (>=0.3.59,<0.4.0)
Requires-Dist: pyspark (==3.1.3)
Requires-Dist: pytest (==6.2.5)
Requires-Dist: pytest-asyncio (==0.16)
Requires-Dist: pytest-cov (==2.12.1)
Requires-Dist: pytest-mock (==3.6.1)
Requires-Dist: pytest-sugar (>=0.9.4,<0.10.0)
Requires-Dist: rich (>=11.1.0,<12.0.0)
Requires-Dist: types-PyYAML (>=6.0.4,<7.0.0)
Requires-Dist: typing-extensions (>=4.1.1,<5.0.0)
Project-URL: Repository, https://github.com/AbsaOSS/pramen
